intro/d_ff.v
module d_ff (
    output reg q, // only "reg" (stores data) can be assigned in always or initial block
    input d,
    input clk
);

always @ (posedge clk) begin
    q <= d;
end

endmodule

intro/d_ff_tb.v
module d_ff_tb;

reg d, clk;
wire q;

// instantiate d flip-flop
d_ff dut (
    .q(q),
    .d(d),
    .clk(clk)
);

// clock generation
always #5 clk = ~clk;

// test bench init
initial begin
    $dumpfile("d_ff.fsdb"); // for nWave
    $dumpvars(0, d_ff_tb);

    // initialize inputs
    d = 0;
    clk = 0;

    #10 d = 1;
    #10 d = 0;
    #10 d = 1;

    #10 $finish;
end

endmodule

intro/d_ff.vcd
$date
	Thu Sep 04 15:37:44 2025
$end
$version
	Icarus Verilog
$end
$timescale
	1ps
$end
$scope module d_ff_tb $end
$var wire 1 ! q $end
$var reg 1 " clk $end
$var reg 1 # d $end
$scope module dut $end
$var wire 1 " clk $end
$var wire 1 # d $end
$var reg 1 ! q $end
$upscope $end
$upscope $end
$enddefinitions $end
$comment Show the parameter values. $end
$dumpall
$end
#0
$dumpvars
0#
0"
x!
$end
#5000
0!
1"
#10000
0"
1#
#15000
1!
1"
#20000
0"
0#
#25000
0!
1"
#30000
0"
1#
#35000
1!
1"
